swiplserver/__init__.py
swiplserver/prologmqi.py
swiplserver-1.0.2.dist-info/LICENSE
swiplserver-1.0.2.dist-info/METADATA
swiplserver-1.0.2.dist-info/WHEEL
swiplserver-1.0.2.dist-info/top_level.txt
swiplserver-1.0.2.dist-info/RECORD
