Metadata-Version: 2.1
Name: swiplserver
Version: 1.0.2
Summary: swiplserver integrates SWI Prolog with Python.
Home-page: https://github.com/SWI-Prolog/packages-mqi
Author: Eric Zinda
Author-email: ericz@inductorsoftware.com
License: UNKNOWN
Project-URL: Bug Tracker, https://github.com/SWI-Prolog/packages-mqi/issues
Project-URL: Documentation, https://www.swi-prolog.org/packages/mqi/prologmqi.html
Platform: UNKNOWN
Classifier: Programming Language :: Python :: 3.7
Classifier: License :: OSI Approved :: MIT License
Classifier: Operating System :: OS Independent
Requires-Python: >=3.7
License-File: LICENSE
